<?xml version="1.0" encoding="utf-8" ?>
<dwsync>
<file name="background.jpg" server="ftp.householdasecology.org//public_html/indigodesign.me/QSY/" local="129669919009234026" remote="129684504000000000" />
<file name="chrome.jpg" server="ftp.householdasecology.org//public_html/indigodesign.me/QSY/" local="129669919009244027" remote="129684504000000000" />
<file name="firefox.jpg" server="ftp.householdasecology.org//public_html/indigodesign.me/QSY/" local="129669919009254027" remote="129684504000000000" />
<file name="ie8.jpg" server="ftp.householdasecology.org//public_html/indigodesign.me/QSY/" local="129669919009264028" remote="129684504000000000" />
<file name="opera.jpg" server="ftp.householdasecology.org//public_html/indigodesign.me/QSY/" local="129669919009314031" remote="129684504000000000" />
<file name="safari.jpg" server="ftp.householdasecology.org//public_html/indigodesign.me/QSY/" local="129669919009334032" remote="129684504000000000" />
<file name="warning.jpg" server="ftp.householdasecology.org//public_html/indigodesign.me/QSY/" local="129669919009374034" remote="129684504000000000" />
<file name="warning.png" server="ftp.householdasecology.org//public_html/indigodesign.me/QSY/" local="129669919009384035" remote="129684504000000000" />
<file name="background.jpg" server="ftp.householdasecology.org//public_html/indigodesign.me/game/" local="129669919009234026" remote="129688096800000000" />
<file name="chrome.jpg" server="ftp.householdasecology.org//public_html/indigodesign.me/game/" local="129669919009244027" remote="129688096800000000" />
<file name="firefox.jpg" server="ftp.householdasecology.org//public_html/indigodesign.me/game/" local="129669919009254027" remote="129688096800000000" />
<file name="ie8.jpg" server="ftp.householdasecology.org//public_html/indigodesign.me/game/" local="129669919009264028" remote="129688096800000000" />
<file name="opera.jpg" server="ftp.householdasecology.org//public_html/indigodesign.me/game/" local="129669919009314031" remote="129688096800000000" />
<file name="safari.jpg" server="ftp.householdasecology.org//public_html/indigodesign.me/game/" local="129669919009334032" remote="129688096800000000" />
<file name="warning.jpg" server="ftp.householdasecology.org//public_html/indigodesign.me/game/" local="129669919009374034" remote="129688096800000000" />
<file name="warning.png" server="ftp.householdasecology.org//public_html/indigodesign.me/game/" local="129669919009384035" remote="129688096800000000" />
<file name="background.jpg" server="ftp.householdasecology.org" local="129669919009234026" remote="129970467000000000" />
<file name="chrome.jpg" server="ftp.householdasecology.org" local="129669919009244027" remote="129970467000000000" />
<file name="firefox.jpg" server="ftp.householdasecology.org" local="129669919009254027" remote="129970467000000000" />
<file name="ie8.jpg" server="ftp.householdasecology.org" local="129669919009264028" remote="129970467000000000" />
<file name="opera.jpg" server="ftp.householdasecology.org" local="129669919009314031" remote="129970467000000000" />
<file name="safari.jpg" server="ftp.householdasecology.org" local="129669919009334032" remote="129970467000000000" />
<file name="warning.jpg" server="ftp.householdasecology.org" local="129669919009374034" remote="129970467000000000" />
<file name="warning.png" server="ftp.householdasecology.org" local="129669919009384035" remote="129970467000000000" />
</dwsync>